{"c":["app/(store)/page","app/(store)/layout","app/layout","webpack"],"r":[],"m":["(app-pages-browser)/./node_modules/lucide-react/dist/esm/icons/package.js","(app-pages-browser)/./node_modules/next/dist/build/webpack/loaders/next-flight-client-entry-loader.js?modules=%7B%22request%22%3A%22%2FUsers%2Fmuskankhan%2FProjects%2Fecommerce-app%2Fcontext%2FCartContext.tsx%22%2C%22ids%22%3A%5B%22CartProvider%22%5D%7D&modules=%7B%22request%22%3A%22%2FUsers%2Fmuskankhan%2FProjects%2Fecommerce-app%2Fnode_modules%2Fnext%2Ffont%2Fgoogle%2Ftarget.css%3F%7B%5C%22path%5C%22%3A%5C%22app%2Flayout.tsx%5C%22%2C%5C%22import%5C%22%3A%5C%22Cormorant_Garamond%5C%22%2C%5C%22arguments%5C%22%3A%5B%7B%5C%22subsets%5C%22%3A%5B%5C%22latin%5C%22%5D%2C%5C%22weight%5C%22%3A%5B%5C%22300%5C%22%2C%5C%22400%5C%22%2C%5C%22500%5C%22%2C%5C%22600%5C%22%5D%2C%5C%22variable%5C%22%3A%5C%22--font-display%5C%22%2C%5C%22display%5C%22%3A%5C%22swap%5C%22%7D%5D%2C%5C%22variableName%5C%22%3A%5C%22cormorant%5C%22%7D%22%2C%22ids%22%3A%5B%5D%7D&modules=%7B%22request%22%3A%22%2FUsers%2Fmuskankhan%2FProjects%2Fecommerce-app%2Fnode_modules%2Fnext%2Ffont%2Fgoogle%2Ftarget.css%3F%7B%5C%22path%5C%22%3A%5C%22app%2Flayout.tsx%5C%22%2C%5C%22import%5C%22%3A%5C%22DM_Sans%5C%22%2C%5C%22arguments%5C%22%3A%5B%7B%5C%22subsets%5C%22%3A%5B%5C%22latin%5C%22%5D%2C%5C%22weight%5C%22%3A%5B%5C%22300%5C%22%2C%5C%22400%5C%22%2C%5C%22500%5C%22%2C%5C%22600%5C%22%5D%2C%5C%22variable%5C%22%3A%5C%22--font-body%5C%22%2C%5C%22display%5C%22%3A%5C%22swap%5C%22%7D%5D%2C%5C%22variableName%5C%22%3A%5C%22dmSans%5C%22%7D%22%2C%22ids%22%3A%5B%5D%7D&modules=%7B%22request%22%3A%22%2FUsers%2Fmuskankhan%2FProjects%2Fecommerce-app%2Fapp%2Fglobals.css%22%2C%22ids%22%3A%5B%5D%7D&server=false!","(app-pages-browser)/./node_modules/next/dist/compiled/mini-css-extract-plugin/hmr/hotModuleReplacement.js","(app-pages-browser)/./node_modules/next/font/google/target.css?{\"path\":\"app/layout.tsx\",\"import\":\"Cormorant_Garamond\",\"arguments\":[{\"subsets\":[\"latin\"],\"weight\":[\"300\",\"400\",\"500\",\"600\"],\"variable\":\"--font-display\",\"display\":\"swap\"}],\"variableName\":\"cormorant\"}","(app-pages-browser)/./node_modules/next/font/google/target.css?{\"path\":\"app/layout.tsx\",\"import\":\"DM_Sans\",\"arguments\":[{\"subsets\":[\"latin\"],\"weight\":[\"300\",\"400\",\"500\",\"600\"],\"variable\":\"--font-body\",\"display\":\"swap\"}],\"variableName\":\"dmSans\"}"]}